bits/__init__.py
bits/progressbar/__init__.py
bits_progressbar-1.0.dist-info/METADATA
bits_progressbar-1.0.dist-info/RECORD
bits_progressbar-1.0.dist-info/WHEEL
bits_progressbar-1.0.dist-info/top_level.txt
