Metadata-Version: 2.1
Name: bits-progressbar
Version: 1.0
Summary: BITS Progressbar
Home-page: UNKNOWN
Author: Lukas Karlsson
Author-email: karlsson@broadinstitute.org
License: Apache Software License
Platform: UNKNOWN
Requires-Dist: progressbar-latest
